odoo/addons/base_country_state_translatable/README.rst
odoo/addons/base_country_state_translatable/__init__.py
odoo/addons/base_country_state_translatable/__manifest__.py
odoo/addons/base_country_state_translatable/i18n/da.po
odoo/addons/base_country_state_translatable/i18n/de.po
odoo/addons/base_country_state_translatable/i18n/es.po
odoo/addons/base_country_state_translatable/i18n/fr.po
odoo/addons/base_country_state_translatable/i18n/hr_HR.po
odoo/addons/base_country_state_translatable/i18n/it.po
odoo/addons/base_country_state_translatable/i18n/pt_BR.po
odoo/addons/base_country_state_translatable/i18n/sl.po
odoo/addons/base_country_state_translatable/models/__init__.py
odoo/addons/base_country_state_translatable/models/res_country.py
odoo11_addon_base_country_state_translatable-11.0.1.0.0.dist-info/DESCRIPTION.rst
odoo11_addon_base_country_state_translatable-11.0.1.0.0.dist-info/METADATA
odoo11_addon_base_country_state_translatable-11.0.1.0.0.dist-info/RECORD
odoo11_addon_base_country_state_translatable-11.0.1.0.0.dist-info/WHEEL
odoo11_addon_base_country_state_translatable-11.0.1.0.0.dist-info/metadata.json
odoo11_addon_base_country_state_translatable-11.0.1.0.0.dist-info/top_level.txt
